{"lang":"en","book":"psa","chapter":6,"verses":[{"v":1,"t":"O Jehovah, rebuke me not in thine anger, Neither chasten me in thy hot displeasure."},{"v":2,"t":"Have mercy upon me, O Jehovah; for I am withered away: O Jehovah, heal me; for my bones are troubled."},{"v":3,"t":"My soul also is sore troubled: And thou, O Jehovah, how long?"},{"v":4,"t":"Return, O Jehovah, deliver my soul: Save me for thy lovingkindness’ sake."},{"v":5,"t":"For in death there is no remembrance of thee: In Sheol who shall give thee thanks?"},{"v":6,"t":"I am weary with my groaning; Every night make I my bed to swim; I water my couch with my tears."},{"v":7,"t":"Mine eye wasteth away because of grief; It waxeth old because of all mine adversaries."},{"v":8,"t":"Depart from me, all ye workers of iniquity; For Jehovah hath heard the voice of my weeping."},{"v":9,"t":"Jehovah hath heard my supplication; Jehovah will receive my prayer."},{"v":10,"t":"All mine enemies shall be put to shame and sore troubled: They shall turn back, they shall be put to shame suddenly."}]}