{"lang":"th","book":"job","chapter":29,"verses":[{"v":1,"t":"แล้วโยบก็กล่าวกลอนภาษิตของท่านอีกว่า"},{"v":2,"t":"“โอ ข้าอยากจะอยู่อย่างแต่ละเดือนที่ผ่านไป อย่างในสมัยเมื่อพระเจ้าทรงพิทักษ์ข้า"},{"v":3,"t":"เมื่อประทีปของพระองค์ส่องเหนือศีรษะข้า และข้าเดินฝ่าความมืดไปด้วยความสว่างของพระองค์"},{"v":4,"t":"อย่างข้าเมื่อครั้งยังหนุ่มแน่นอยู่ เมื่อความลึกลับแห่งพระเจ้าทรงอยู่เหนือเต็นท์ของข้า"},{"v":5,"t":"เมื่อองค์ผู้ทรงมหิทธิฤทธิ์ยังอยู่กับข้า และลูกหลานห้อมล้อมข้า"},{"v":6,"t":"เมื่อข้าล้างย่างเท้าของข้าด้วยเนยข้น และก้อนหินเทธารน้ำมันออกให้ข้า"},{"v":7,"t":"เมื่อข้าออกมายังประตูเมือง เมื่อข้าเตรียมที่นั่งของข้าที่ถนน"},{"v":8,"t":"คนหนุ่มๆเห็นข้าแล้วก็หลีกไป คนสูงอายุลุกขึ้นยืน"},{"v":9,"t":"เจ้านายหยุดพูด เอามือปิดปากของตนไว้"},{"v":10,"t":"เสียงของขุนนางก็สงบลง และลิ้นของเขาก็เกาะติดเพดานปาก"},{"v":11,"t":"เมื่อหูได้ยินแล้ว ต่างก็ว่าข้าเป็นสุข และเมื่อตาดู ก็ยกย่องข้า"},{"v":12,"t":"เพราะว่าข้าช่วยคนยากจนที่ร้องให้ช่วย และเด็กกำพร้าพ่อที่ไม่มีใครอุปถัมภ์เขา"},{"v":13,"t":"พรของคนที่จวนพินาศก็มาถึงข้า และข้าเป็นเหตุให้จิตใจของหญิงม่ายร้องเพลงด้วยความชื่นบาน"},{"v":14,"t":"ข้าสวมความชอบธรรม และมันก็ห่อหุ้มข้าไว้ ความยุติธรรมของข้าเหมือนเสื้อคลุมและผ้าโพกศีรษะ"},{"v":15,"t":"ข้าเป็นนัยน์ตาให้คนตาบอด และเป็นเท้าให้คนง่อย"},{"v":16,"t":"ข้าเป็นบิดาให้คนขัดสน และข้าสอบสวนเรื่องของผู้ที่ข้าไม่รู้จัก"},{"v":17,"t":"ข้าหักขากรรไกรของคนชั่ว และได้ดึงเอาเหยื่อจากฟันของเขา"},{"v":18,"t":"แล้วข้าคิดว่า ‘ข้าจะตายในรังของข้า และข้าจะทวีวันเวลาของข้าอย่างทราย"},{"v":19,"t":"รากของข้าจะแผ่ไปถึงน้ำ มีน้ำค้างบนกิ่งของข้าตลอดคืน"},{"v":20,"t":"สง่าราศีของข้าสดชื่นอยู่กับข้า และคันธนูของข้าใหม่เสมออยู่ในมือข้า’"},{"v":21,"t":"คนทั้งหลายเงี่ยหูฟังข้าและคอยอยู่ และเงียบอยู่ฟังคำปรึกษาของข้า"},{"v":22,"t":"หลังจากที่ข้าพูดแล้ว เขาก็ไม่พูดอีกเลย และคำของข้าก็กลั่นลงมาเหนือเขา"},{"v":23,"t":"เขาคอยข้าเหมือนคอยฝน เขาอ้าปากของเขาเหมือนอย่างรอรับน้ำฝนชุกปลายฤดู"},{"v":24,"t":"ถ้าข้าหัวเราะเยาะเขา เขาก็ไม่ยอมเชื่อ และสีหน้าอันผ่องใสของข้า เขาก็มิได้ทำให้หม่นหมองลง"},{"v":25,"t":"ข้าเลือกทางให้เขา และนั่งเป็นหัวหน้า และอยู่อย่างกษัตริย์ท่ามกลางกองทหาร อย่างผู้ที่ปลอบโยนคนที่คร่ำครวญ”"}]}